Metadata-Version: 1.0
Name: distributions-ahmed
Version: 1.0
Summary: Gausssian and Binomaial distribution
Home-page: UNKNOWN
Author: UNKNOWN
Author-email: UNKNOWN
License: UNKNOWN
Platform: UNKNOWN
